autograd/__init__.py
autograd/context.py
autograd/function.py
autograd/grad_mode.py
autograd/ops.py
autograd/variable.py
puretorch/.DS_Store
puretorch/__init__.py
puretorch/tensor.py
puretorch/nn/.DS_Store
puretorch/nn/__init__.py
puretorch/nn/functional.py
puretorch/nn/linear.py
puretorch/nn/module.py
puretorch/nn/parameter.py
puretorch/nn/relu.py
puretorch/nn/sequential.py
puretorch/nn/softmax.py
puretorch/nn/tanh.py
puretorch/nn/utils.py
puretorch/optim/__init__.py
puretorch/optim/optimizer.py
puretorch/optim/sgd.py
puretorch/utils/tensor_utils.py
puretorch/utils/viz.py
puretorch-1.1.1.dist-info/licenses/LICENSE
tests/__init__.py
tests/autograd_tests.py
tests/tensor_tests.py
puretorch-1.1.1.dist-info/METADATA
puretorch-1.1.1.dist-info/WHEEL
puretorch-1.1.1.dist-info/top_level.txt
puretorch-1.1.1.dist-info/RECORD
